i3_sway_switch_window/__init__.py
i3_sway_switch_window/__main__.py
i3_sway_switch_window/__version__.py
i3_sway_switch_window/browser_tab_list.py
i3_sway_switch_window/config.py
i3_sway_switch_window/display_error_message.py
i3_sway_switch_window/emacs_buffer_lists.py
i3_sway_switch_window/emacs_recentf_list.py
i3_sway_switch_window/get_nyxt_title_url.py
i3_sway_switch_window/get_qutebrowser_title_url.py
i3_sway_switch_window/i3_do_add.py
i3_sway_switch_window/i3_do_switch.py
i3_sway_switch_window/main.py
i3_sway_switch_window/wm_window_list.py
i3_sway_switch_window-0.3.0.dist-info/METADATA
i3_sway_switch_window-0.3.0.dist-info/WHEEL
i3_sway_switch_window-0.3.0.dist-info/entry_points.txt
i3_sway_switch_window-0.3.0.dist-info/licenses/LICENSE
i3_sway_switch_window-0.3.0.dist-info/RECORD
