Metadata-Version: 2.1
Name: i3_sway_switch_window
Version: 0.3.0
Summary: In i3wm, or sway, replace current window with emacs buffer, browser tab or other window
Project-URL: Homepage, https://github.com/johanwiden/i3-sway-switch-window
Project-URL: Bug Tracker, https://github.com/johanwiden/i3-sway-switch-window/issues
Author-email: Johan Widén <j.e.widen@gmail.com>
License-File: LICENSE
Classifier: Development Status :: 4 - Beta
Classifier: Environment :: X11 Applications
Classifier: Intended Audience :: End Users/Desktop
Classifier: License :: OSI Approved :: MIT License
Classifier: Natural Language :: English
Classifier: Operating System :: POSIX
Classifier: Programming Language :: Python :: 3.8
Classifier: Programming Language :: Python :: 3.9
Classifier: Programming Language :: Python :: 3.10
Classifier: Programming Language :: Python :: 3.11
Classifier: Programming Language :: Unix Shell
Classifier: Topic :: Desktop Environment :: Window Managers
Requires-Python: >=3.8
Requires-Dist: i3ipc
Requires-Dist: psutil
Requires-Dist: pyyaml
